osrswiki_images/__init__.py
osrswiki_images/cli.py
osrswiki_images/client.py
osrswiki_images/data/prayers.csv
osrswiki_images/data/slayer_rewards.csv
osrswiki_images-0.1.4.dist-info/licenses/LICENSE
osrswiki_images-0.1.4.dist-info/METADATA
osrswiki_images-0.1.4.dist-info/WHEEL
osrswiki_images-0.1.4.dist-info/entry_points.txt
osrswiki_images-0.1.4.dist-info/top_level.txt
osrswiki_images-0.1.4.dist-info/RECORD
