Metadata-Version: 2.4
Name: osrswiki-images
Version: 0.1.4
Summary: Resolve OSRS names to wiki and image URLs (items, spells, construction, quests, skills, plus curated prayers/slayer rewards).
Author: Mads Balto
License: MIT License
Project-URL: Homepage, https://github.com/Madssb/osrswiki-images
Project-URL: Issues, https://github.com/Madssb/osrswiki-images/issues
Keywords: runescape,osrs,wiki,images,api,cli
Classifier: Programming Language :: Python :: 3
Classifier: Programming Language :: Python :: 3 :: Only
Classifier: License :: OSI Approved :: MIT License
Classifier: Operating System :: OS Independent
Classifier: Intended Audience :: Developers
Classifier: Topic :: Internet :: WWW/HTTP
Classifier: Topic :: Utilities
Requires-Python: >=3.11
License-File: LICENSE
Requires-Dist: requests>=2.31
Requires-Dist: pandas>=2.0
Requires-Dist: backoff
Dynamic: license-file
